{"sections":{"banner":{"type":"main-collection-banner","disabled":true,"settings":{"show_collection_description":true,"show_collection_image":false,"color_scheme":"scheme-1"}},"product-grid":{"type":"main-collection-product-grid","settings":{"products_per_page":12,"columns_desktop":3,"columns_mobile":"1","color_scheme":"scheme-1","image_ratio":"square","image_shape":"default","show_secondary_image":true,"show_vendor":false,"show_rating":false,"quick_add":"none","enable_filtering":true,"filter_type":"vertical","enable_sorting":true,"padding_top":80,"padding_bottom":80}},"new_image_overlay_JQHzdm":{"type":"new-image-overlay","blocks":{"image_Dg8cgG":{"type":"image","settings":{"image":"shopify:\/\/shop_images\/Engagement_Rings_f51d6560-4233-4eec-a1a5-6603b1c7ed86.png","image_m":"shopify:\/\/shop_images\/Engagement_Rings_3_ea5b320a-74c2-40e9-a05e-14c4529f76d4.png","title":"Engagement Rings in<em> Boca Raton<\/em>","text":"We make it easy for you to get exactly what you’re <em>looking for and take great pride in every step of<\/em> the process."}},"image_Yykp6F":{"type":"image","settings":{"image":"shopify:\/\/shop_images\/Engagement_Rings_1_ebb186a9-78e2-4b46-bfa7-596c9cab7604.png","image_m":"shopify:\/\/shop_images\/Engagement_Rings_2_d3867174-c9a7-4f9a-a76c-f1524d2945a0.png","title":"<em>Custom Engagement <\/em>Ring Design Boca Raton","text":"We make it easy for you to get exactly what you’re<em> looking for and take great pride in every step of the<\/em> process."}}},"block_order":["image_Dg8cgG","image_Yykp6F"],"name":"New Image Overlay","settings":{"full_width":false,"margin_top":0,"margin_bottom":0,"padding_top":0,"padding_bottom":48,"margin_top_m":0,"margin_bottom_m":0,"padding_top_m":0,"padding_bottom_m":32}}},"order":["banner","product-grid","new_image_overlay_JQHzdm"]}